cfmUtils/__init__.py
cfmUtils/config.py
cfmUtils/io.py
cfmUtils/logger.py
cfmUtils/runtime.py
cfmUtils/saver.py
cfmUtils/base/__init__.py
cfmUtils/base/dataParallel.py
cfmUtils/base/decoratorContextManager.py
cfmUtils/base/freqHook.py
cfmUtils/base/module.py
cfmUtils/base/registrar.py
cfmUtils/base/restorable.py
cfmUtils/datasets/__init__.py
cfmUtils/datasets/wrappers.py
cfmUtils/metrics/__init__.py
cfmUtils/metrics/helpers.py
cfmUtils/metrics/pairwise.py
cfmUtils/vision/__init__.py
cfmUtils/vision/colorSpace.py
cfmUtils/vision/utils.py
test/__init__.py
test/conftest.py
test/test_base.py
test/test_dataset.py
test/test_vision.py
cfmUtils-0.1.2.dist-info/LICENSE
cfmUtils-0.1.2.dist-info/METADATA
cfmUtils-0.1.2.dist-info/WHEEL
cfmUtils-0.1.2.dist-info/top_level.txt
cfmUtils-0.1.2.dist-info/RECORD
