Metadata-Version: 2.1
Name: cfmUtils
Version: 0.1.2
Summary: My package description
Home-page: https://github.com/cfm-uestc/cfmUtils
Author: Xiaosu Zhu
Author-email: aurora.studio@outlook.com
License: Apache-2.0 License
Keywords: Utilities,Utils
Platform: UNKNOWN
Classifier: Development Status :: 3 - Alpha
Classifier: Intended Audience :: Developers
Classifier: Topic :: Software Development :: Libraries
Classifier: License :: OSI Approved :: Apache Software License
Classifier: Programming Language :: Python :: 3.7
Classifier: Programming Language :: Python :: 3.8
Requires-Python: >=3.7
Requires-Dist: torch (>=1.7)
Requires-Dist: tqdm
Requires-Dist: nvidia-ml-py3
